nardlpy/__init__.py
nardlpy/nardl.py
nardlpy-1.0.0.dist-info/licenses/LICENSE.txt
nardlpy-1.0.0.dist-info/METADATA
nardlpy-1.0.0.dist-info/WHEEL
nardlpy-1.0.0.dist-info/top_level.txt
nardlpy-1.0.0.dist-info/RECORD
