Metadata-Version: 2.4
Name: nardlpy
Version: 1.0.0
Summary: NARDL and Fourier NARDL estimation and diagnostic toolkit in Python.
Author: Dr. Taha Zaghdoudi
Author-email: zedtaha@gmail.com
License: MIT
Requires-Python: >=3.8
License-File: LICENSE.txt
Requires-Dist: numpy
Requires-Dist: pandas
Requires-Dist: scipy
Requires-Dist: statsmodels
Requires-Dist: matplotlib
Dynamic: author
Dynamic: author-email
Dynamic: description
Dynamic: description-content-type
Dynamic: license
Dynamic: license-file
Dynamic: requires-dist
Dynamic: requires-python
Dynamic: summary
